PipelineProfiler/__init__.py
PipelineProfiler/_comm_api.py
PipelineProfiler/_demodata.py
PipelineProfiler/_graph_matching.py
PipelineProfiler/_helpers.py
PipelineProfiler/_import_autosklearn.py
PipelineProfiler/_plot_pipeline_matrix.py
PipelineProfiler/_plot_pipeline_node_link.py
PipelineProfiler/_powerset_analysis.py
PipelineProfiler/_similarity_flooding.py
PipelineProfiler/pipeline_merge.py
PipelineProfiler/build/pipelineVis.js
PipelineProfiler/data/teaser_data_heartstatlog.json
pipelineprofiler-0.1.18.dist-info/LICENSE
pipelineprofiler-0.1.18.dist-info/METADATA
pipelineprofiler-0.1.18.dist-info/WHEEL
pipelineprofiler-0.1.18.dist-info/top_level.txt
pipelineprofiler-0.1.18.dist-info/RECORD
