Metadata-Version: 2.1
Name: pipelineprofiler
Version: 0.1.18
Summary: Pipeline Profiler tool. Enables the exploration of D3M pipelines in Jupyter Notebooks
Home-page: https://github.com/VIDA-NYU/PipelineVis
Author: Jorge Piazentin Ono, Sonia Castelo, Roque Lopez, Enrico Bertini, Juliana Freire, Claudio Silva
Author-email: jorgehpo@nyu.edu
License: UNKNOWN
Platform: UNKNOWN
Classifier: Programming Language :: Python :: 3
Classifier: License :: OSI Approved :: BSD License
Classifier: Operating System :: OS Independent
Requires-Python: >=3.6
License-File: LICENSE
Requires-Dist: python-dateutil
Requires-Dist: numpy
Requires-Dist: scipy
Requires-Dist: scikit-learn
Requires-Dist: networkx
Requires-Dist: notebook
